migrations/__init__.py
yagnesh07-0.0.1.dist-info/LICENSE
yagnesh07-0.0.1.dist-info/METADATA
yagnesh07-0.0.1.dist-info/WHEEL
yagnesh07-0.0.1.dist-info/top_level.txt
yagnesh07-0.0.1.dist-info/RECORD
